AUTHORS.rst
CONTRIBUTING.rst
HISTORY.rst
LICENSE
MANIFEST.in
README.rst
requirements.txt
setup.cfg
setup.py
docs/Makefile
docs/authors.rst
docs/conf.py
docs/contributing.rst
docs/history.rst
docs/hubward.rst
docs/index.rst
docs/installation.rst
docs/make.bat
docs/modules.rst
docs/readme.rst
hubward/__init__.py
hubward/generate_config_from_schema.py
hubward/hubward
hubward/liftover.py
hubward/log.py
hubward/models.py
hubward/utils.py
hubward/version.py
hubward.egg-info/PKG-INFO
hubward.egg-info/SOURCES.txt
hubward.egg-info/dependency_links.txt
hubward.egg-info/not-zip-safe
hubward.egg-info/requires.txt
hubward.egg-info/top_level.txt
resources/a.dat
resources/b.dat
resources/dat2bigbed.sh
resources/get-data.bash
resources/group_schema.yaml
resources/metadata_builder_template.py
resources/metadata_schema.yaml
resources/process_template.py
resources/process_template.sh
tests/__init__.py
tests/test_hubward.py
tests/cases/simple/metadata-builder.py