Metadata-Version: 1.1
Name: hubward
Version: 0.2.2
Summary: Manage the visualization of large amounts of other people's [often messy] genomics data
Home-page: https://github.com/daler/hubward
Author: Ryan Dale
Author-email: dalerr@niddk.nih.gov
License: BSD
Keywords: hubward
Platform: UNKNOWN
Classifier: Development Status :: 2 - Pre-Alpha
Classifier: Intended Audience :: Developers
Classifier: License :: OSI Approved :: BSD License
Classifier: Natural Language :: English
Classifier: Topic :: Scientific/Engineering :: Bio-Informatics
Classifier: Programming Language :: Python :: 2
Classifier: Programming Language :: Python :: 2.6
Classifier: Programming Language :: Python :: 2.7
Classifier: Programming Language :: Python :: 3
Classifier: Programming Language :: Python :: 3.3
Classifier: Programming Language :: Python :: 3.4
